songtradr_api_client_python/__init__.py
songtradr_api_client_python/api_client.py
songtradr_api_client_python/api_response.py
songtradr_api_client_python/configuration.py
songtradr_api_client_python/exceptions.py
songtradr_api_client_python/py.typed
songtradr_api_client_python/rest.py
songtradr_api_client_python/api/__init__.py
songtradr_api_client_python/api/allowed_values_api.py
songtradr_api_client_python/api/recording_api.py
songtradr_api_client_python/api/user_api.py
songtradr_api_client_python/models/__init__.py
songtradr_api_client_python/models/category_minimal_dto.py
songtradr_api_client_python/models/config_access_dto.py
songtradr_api_client_python/models/config_identifier_dto.py
songtradr_api_client_python/models/contributor_type_dto.py
songtradr_api_client_python/models/error_response.py
songtradr_api_client_python/models/field_summary_dto.py
songtradr_api_client_python/models/file_dto.py
songtradr_api_client_python/models/file_list_dto.py
songtradr_api_client_python/models/file_small_dto.py
songtradr_api_client_python/models/file_upload_dto.py
songtradr_api_client_python/models/file_w_ith_url_dto.py
songtradr_api_client_python/models/files_summary_dto.py
songtradr_api_client_python/models/forgot_password_dto.py
songtradr_api_client_python/models/genre_dto.py
songtradr_api_client_python/models/genre_minimal_dto.py
songtradr_api_client_python/models/genres_summary_dto.py
songtradr_api_client_python/models/init_put_recording_audio_dto.py
songtradr_api_client_python/models/jwt_token_dto.py
songtradr_api_client_python/models/login_dto.py
songtradr_api_client_python/models/musical_features_dto.py
songtradr_api_client_python/models/party_small_dto.py
songtradr_api_client_python/models/recording_genre_prediction_dto.py
songtradr_api_client_python/models/recording_medium_dto.py
songtradr_api_client_python/models/recording_minimal_with_taggrams_dto.py
songtradr_api_client_python/models/recording_minimal_with_tagstrengths_dto.py
songtradr_api_client_python-3.0.0.dist-info/METADATA
songtradr_api_client_python-3.0.0.dist-info/WHEEL
songtradr_api_client_python-3.0.0.dist-info/top_level.txt
songtradr_api_client_python-3.0.0.dist-info/RECORD
