Metadata-Version: 2.1
Name: songtradr-api-client-python
Version: 3.0.0
Summary: Songtradr API
Home-page: https://github.com/songtradr/songtradr-python-api-client-docs
Author: Songtradr Inc.
Author-email: info@songtradr.com
Keywords: OpenAPI,OpenAPI-Generator,Songtradr API
Requires-Dist: urllib3 <2.1.0,>=1.25.3
Requires-Dist: python-dateutil
Requires-Dist: pydantic >=2
Requires-Dist: typing-extensions >=4.7.1
